[ {
  "name" : "Maks Verver",
  "points" : 2203,
  "maxPoints" : 235,
  "minPoints" : 206,
  "averagePoints" : 220.3,
  "standardDeviationOfPoints" : 9.62,
  "wins" : 10,
  "draws" : 0,
  "losses" : 0,
  "fails" : 0,
  "squeakerWins" : 0,
  "squeakerLosses" : 0,
  "subjectivePlayerType" : "Stronger"
}, {
  "name" : "Maaike van der Laan",
  "points" : 872,
  "maxPoints" : 98,
  "minPoints" : 78,
  "averagePoints" : 87.2,
  "standardDeviationOfPoints" : 5.67,
  "wins" : 0,
  "draws" : 0,
  "losses" : 10,
  "fails" : 0,
  "squeakerWins" : 0,
  "squeakerLosses" : 1,
  "subjectivePlayerType" : "Weaker"
}, {
  "name" : "Marc Oldenhof",
  "points" : 2202,
  "maxPoints" : 237,
  "minPoints" : 202,
  "averagePoints" : 220.2,
  "standardDeviationOfPoints" : 10.17,
  "wins" : 10,
  "draws" : 0,
  "losses" : 0,
  "fails" : 0,
  "squeakerWins" : 1,
  "squeakerLosses" : 0,
  "subjectivePlayerType" : "Stronger"
}, {
  "name" : "Pham Thanh Dat",
  "points" : 670,
  "maxPoints" : 94,
  "minPoints" : 0,
  "averagePoints" : 67.0,
  "standardDeviationOfPoints" : 34.44,
  "wins" : 0,
  "draws" : 0,
  "losses" : 10,
  "fails" : 2,
  "squeakerWins" : 0,
  "squeakerLosses" : 0,
  "subjectivePlayerType" : "Weaker"
}, {
  "name" : "Niklas Een",
  "points" : 2193,
  "maxPoints" : 234,
  "minPoints" : 209,
  "averagePoints" : 219.3,
  "standardDeviationOfPoints" : 7.38,
  "wins" : 10,
  "draws" : 0,
  "losses" : 0,
  "fails" : 0,
  "squeakerWins" : 0,
  "squeakerLosses" : 0,
  "subjectivePlayerType" : "Stronger"
}, {
  "name" : "Bas van der Ven",
  "points" : 1176,
  "maxPoints" : 150,
  "minPoints" : 0,
  "averagePoints" : 117.6,
  "standardDeviationOfPoints" : 47.05,
  "wins" : 0,
  "draws" : 6,
  "losses" : 4,
  "fails" : 1,
  "squeakerWins" : 0,
  "squeakerLosses" : 0,
  "subjectivePlayerType" : "Weaker"
}, {
  "name" : "Louis Verhaard",
  "points" : 2146,
  "maxPoints" : 224,
  "minPoints" : 204,
  "averagePoints" : 214.6,
  "standardDeviationOfPoints" : 7.55,
  "wins" : 10,
  "draws" : 0,
  "losses" : 0,
  "fails" : 0,
  "squeakerWins" : 0,
  "squeakerLosses" : 0,
  "subjectivePlayerType" : "Stronger"
}, {
  "name" : "Ludo Pulles",
  "points" : 1016,
  "maxPoints" : 201,
  "minPoints" : 86,
  "averagePoints" : 101.6,
  "standardDeviationOfPoints" : 33.27,
  "wins" : 1,
  "draws" : 0,
  "losses" : 9,
  "fails" : 0,
  "squeakerWins" : 1,
  "squeakerLosses" : 0,
  "subjectivePlayerType" : "Weaker"
}, {
  "name" : "Tapani Utriainen",
  "points" : 2236,
  "maxPoints" : 244,
  "minPoints" : 211,
  "averagePoints" : 223.6,
  "standardDeviationOfPoints" : 9.61,
  "wins" : 10,
  "draws" : 0,
  "losses" : 0,
  "fails" : 0,
  "squeakerWins" : 0,
  "squeakerLosses" : 0,
  "subjectivePlayerType" : "Stronger"
}, {
  "name" : "Daniëlle  Philippen",
  "points" : 977,
  "maxPoints" : 208,
  "minPoints" : 76,
  "averagePoints" : 97.7,
  "standardDeviationOfPoints" : 37.25,
  "wins" : 1,
  "draws" : 0,
  "losses" : 9,
  "fails" : 0,
  "squeakerWins" : 0,
  "squeakerLosses" : 0,
  "subjectivePlayerType" : "Weaker"
}, {
  "name" : "Mark ter Brugge",
  "points" : 2211,
  "maxPoints" : 233,
  "minPoints" : 212,
  "averagePoints" : 221.1,
  "standardDeviationOfPoints" : 6.49,
  "wins" : 10,
  "draws" : 0,
  "losses" : 0,
  "fails" : 0,
  "squeakerWins" : 0,
  "squeakerLosses" : 0,
  "subjectivePlayerType" : "Stronger"
}, {
  "name" : "Nur'alya Martosoewondo",
  "points" : 1062,
  "maxPoints" : 213,
  "minPoints" : 64,
  "averagePoints" : 106.2,
  "standardDeviationOfPoints" : 51.38,
  "wins" : 2,
  "draws" : 0,
  "losses" : 8,
  "fails" : 0,
  "squeakerWins" : 1,
  "squeakerLosses" : 0,
  "subjectivePlayerType" : "Weaker"
}, {
  "name" : "Martin Jakobsson",
  "points" : 2160,
  "maxPoints" : 228,
  "minPoints" : 204,
  "averagePoints" : 216.0,
  "standardDeviationOfPoints" : 7.01,
  "wins" : 10,
  "draws" : 0,
  "losses" : 0,
  "fails" : 0,
  "squeakerWins" : 0,
  "squeakerLosses" : 0,
  "subjectivePlayerType" : "Stronger"
}, {
  "name" : "Kirk Brown",
  "points" : 943,
  "maxPoints" : 150,
  "minPoints" : 69,
  "averagePoints" : 94.3,
  "standardDeviationOfPoints" : 29.02,
  "wins" : 0,
  "draws" : 2,
  "losses" : 8,
  "fails" : 0,
  "squeakerWins" : 0,
  "squeakerLosses" : 0,
  "subjectivePlayerType" : "Weaker"
}, {
  "name" : "Jan Nunnink",
  "points" : 2236,
  "maxPoints" : 242,
  "minPoints" : 213,
  "averagePoints" : 223.6,
  "standardDeviationOfPoints" : 8.69,
  "wins" : 10,
  "draws" : 0,
  "losses" : 0,
  "fails" : 0,
  "squeakerWins" : 0,
  "squeakerLosses" : 0,
  "subjectivePlayerType" : "Stronger"
}, {
  "name" : "Maarten Post",
  "points" : 887,
  "maxPoints" : 94,
  "minPoints" : 80,
  "averagePoints" : 88.7,
  "standardDeviationOfPoints" : 4.22,
  "wins" : 0,
  "draws" : 0,
  "losses" : 10,
  "fails" : 0,
  "squeakerWins" : 0,
  "squeakerLosses" : 0,
  "subjectivePlayerType" : "Weaker"
}, {
  "name" : "Pardhav Maradani",
  "points" : 2202,
  "maxPoints" : 235,
  "minPoints" : 206,
  "averagePoints" : 220.2,
  "standardDeviationOfPoints" : 9.54,
  "wins" : 10,
  "draws" : 0,
  "losses" : 0,
  "fails" : 0,
  "squeakerWins" : 0,
  "squeakerLosses" : 0,
  "subjectivePlayerType" : "Stronger"
}, {
  "name" : "Luka Markovic",
  "points" : 816,
  "maxPoints" : 93,
  "minPoints" : 53,
  "averagePoints" : 81.6,
  "standardDeviationOfPoints" : 11.08,
  "wins" : 0,
  "draws" : 0,
  "losses" : 10,
  "fails" : 0,
  "squeakerWins" : 0,
  "squeakerLosses" : 0,
  "subjectivePlayerType" : "Weaker"
}, {
  "name" : "Xavier Botot",
  "points" : 2170,
  "maxPoints" : 232,
  "minPoints" : 208,
  "averagePoints" : 217.0,
  "standardDeviationOfPoints" : 8.25,
  "wins" : 10,
  "draws" : 0,
  "losses" : 0,
  "fails" : 0,
  "squeakerWins" : 0,
  "squeakerLosses" : 0,
  "subjectivePlayerType" : "Stronger"
}, {
  "name" : "Sergei Budkov",
  "points" : 889,
  "maxPoints" : 150,
  "minPoints" : 75,
  "averagePoints" : 88.9,
  "standardDeviationOfPoints" : 21.42,
  "wins" : 0,
  "draws" : 1,
  "losses" : 9,
  "fails" : 0,
  "squeakerWins" : 0,
  "squeakerLosses" : 0,
  "subjectivePlayerType" : "Weaker"
}, {
  "name" : "Alvaro Carrera",
  "points" : 2194,
  "maxPoints" : 231,
  "minPoints" : 208,
  "averagePoints" : 219.4,
  "standardDeviationOfPoints" : 6.25,
  "wins" : 10,
  "draws" : 0,
  "losses" : 0,
  "fails" : 0,
  "squeakerWins" : 0,
  "squeakerLosses" : 0,
  "subjectivePlayerType" : "Stronger"
}, {
  "name" : "Nikita Kurgin",
  "points" : 1038,
  "maxPoints" : 207,
  "minPoints" : 68,
  "averagePoints" : 103.8,
  "standardDeviationOfPoints" : 40.23,
  "wins" : 1,
  "draws" : 1,
  "losses" : 8,
  "fails" : 0,
  "squeakerWins" : 0,
  "squeakerLosses" : 0,
  "subjectivePlayerType" : "Weaker"
}, {
  "name" : "Leopold Tschanter",
  "points" : 2173,
  "maxPoints" : 238,
  "minPoints" : 207,
  "averagePoints" : 217.3,
  "standardDeviationOfPoints" : 8.36,
  "wins" : 10,
  "draws" : 0,
  "losses" : 0,
  "fails" : 0,
  "squeakerWins" : 0,
  "squeakerLosses" : 0,
  "subjectivePlayerType" : "Stronger"
}, {
  "name" : "R4N4R4M4 ",
  "points" : 873,
  "maxPoints" : 94,
  "minPoints" : 76,
  "averagePoints" : 87.3,
  "standardDeviationOfPoints" : 5.25,
  "wins" : 0,
  "draws" : 0,
  "losses" : 10,
  "fails" : 0,
  "squeakerWins" : 0,
  "squeakerLosses" : 0,
  "subjectivePlayerType" : "Weaker"
}, {
  "name" : "Jelle van der Drift",
  "points" : 2165,
  "maxPoints" : 233,
  "minPoints" : 205,
  "averagePoints" : 216.5,
  "standardDeviationOfPoints" : 8.79,
  "wins" : 10,
  "draws" : 0,
  "losses" : 0,
  "fails" : 0,
  "squeakerWins" : 0,
  "squeakerLosses" : 0,
  "subjectivePlayerType" : "Stronger"
}, {
  "name" : "Léo Jean",
  "points" : 1311,
  "maxPoints" : 208,
  "minPoints" : 76,
  "averagePoints" : 131.1,
  "standardDeviationOfPoints" : 53.28,
  "wins" : 3,
  "draws" : 1,
  "losses" : 6,
  "fails" : 0,
  "squeakerWins" : 0,
  "squeakerLosses" : 1,
  "subjectivePlayerType" : "Challenger"
}, {
  "name" : "Stephen Robertson",
  "points" : 2181,
  "maxPoints" : 238,
  "minPoints" : 204,
  "averagePoints" : 218.1,
  "standardDeviationOfPoints" : 9.79,
  "wins" : 10,
  "draws" : 0,
  "losses" : 0,
  "fails" : 0,
  "squeakerWins" : 0,
  "squeakerLosses" : 0,
  "subjectivePlayerType" : "Stronger"
}, {
  "name" : "Gia Bao Ha",
  "points" : 1006,
  "maxPoints" : 206,
  "minPoints" : 74,
  "averagePoints" : 100.6,
  "standardDeviationOfPoints" : 35.89,
  "wins" : 1,
  "draws" : 0,
  "losses" : 9,
  "fails" : 0,
  "squeakerWins" : 0,
  "squeakerLosses" : 1,
  "subjectivePlayerType" : "Weaker"
}, {
  "name" : "Matthias Gelbmann",
  "points" : 2158,
  "maxPoints" : 234,
  "minPoints" : 203,
  "averagePoints" : 215.8,
  "standardDeviationOfPoints" : 9.18,
  "wins" : 10,
  "draws" : 0,
  "losses" : 0,
  "fails" : 0,
  "squeakerWins" : 0,
  "squeakerLosses" : 0,
  "subjectivePlayerType" : "Stronger"
}, {
  "name" : "Joe Rahn",
  "points" : 878,
  "maxPoints" : 95,
  "minPoints" : 81,
  "averagePoints" : 87.8,
  "standardDeviationOfPoints" : 4.42,
  "wins" : 0,
  "draws" : 0,
  "losses" : 10,
  "fails" : 0,
  "squeakerWins" : 0,
  "squeakerLosses" : 0,
  "subjectivePlayerType" : "Weaker"
}, {
  "name" : "Matthijs Tijink",
  "points" : 2162,
  "maxPoints" : 243,
  "minPoints" : 203,
  "averagePoints" : 216.2,
  "standardDeviationOfPoints" : 11.2,
  "wins" : 10,
  "draws" : 0,
  "losses" : 0,
  "fails" : 0,
  "squeakerWins" : 0,
  "squeakerLosses" : 0,
  "subjectivePlayerType" : "Stronger"
}, {
  "name" : "Bart Mol",
  "points" : 1375,
  "maxPoints" : 217,
  "minPoints" : 81,
  "averagePoints" : 137.5,
  "standardDeviationOfPoints" : 58.11,
  "wins" : 4,
  "draws" : 0,
  "losses" : 6,
  "fails" : 0,
  "squeakerWins" : 1,
  "squeakerLosses" : 1,
  "subjectivePlayerType" : "Challenger"
}, {
  "name" : "Marty McScan",
  "points" : 2008,
  "maxPoints" : 232,
  "minPoints" : 150,
  "averagePoints" : 200.8,
  "standardDeviationOfPoints" : 27.01,
  "wins" : 8,
  "draws" : 2,
  "losses" : 0,
  "fails" : 0,
  "squeakerWins" : 1,
  "squeakerLosses" : 0,
  "subjectivePlayerType" : "Stronger"
}, {
  "name" : "Marcel Vlastuin",
  "points" : 2021,
  "maxPoints" : 228,
  "minPoints" : 84,
  "averagePoints" : 202.1,
  "standardDeviationOfPoints" : 40.37,
  "wins" : 9,
  "draws" : 0,
  "losses" : 1,
  "fails" : 0,
  "squeakerWins" : 1,
  "squeakerLosses" : 0,
  "subjectivePlayerType" : "Stronger"
}, {
  "name" : "Abdessamad El Kasimi",
  "points" : 2237,
  "maxPoints" : 232,
  "minPoints" : 219,
  "averagePoints" : 223.7,
  "standardDeviationOfPoints" : 4.71,
  "wins" : 10,
  "draws" : 0,
  "losses" : 0,
  "fails" : 0,
  "squeakerWins" : 0,
  "squeakerLosses" : 0,
  "subjectivePlayerType" : "Stronger"
}, {
  "name" : "Erik Kvanli",
  "points" : 1441,
  "maxPoints" : 219,
  "minPoints" : 86,
  "averagePoints" : 144.1,
  "standardDeviationOfPoints" : 54.68,
  "wins" : 4,
  "draws" : 1,
  "losses" : 5,
  "fails" : 0,
  "squeakerWins" : 0,
  "squeakerLosses" : 1,
  "subjectivePlayerType" : "Challenger"
}, {
  "name" : "Jeremy Sawicki",
  "points" : 2182,
  "maxPoints" : 235,
  "minPoints" : 206,
  "averagePoints" : 218.2,
  "standardDeviationOfPoints" : 8.93,
  "wins" : 10,
  "draws" : 0,
  "losses" : 0,
  "fails" : 0,
  "squeakerWins" : 0,
  "squeakerLosses" : 0,
  "subjectivePlayerType" : "Stronger"
}, {
  "name" : "Vasilii Kuporosov",
  "points" : 1880,
  "maxPoints" : 231,
  "minPoints" : 88,
  "averagePoints" : 188.0,
  "standardDeviationOfPoints" : 42.36,
  "wins" : 7,
  "draws" : 2,
  "losses" : 1,
  "fails" : 0,
  "squeakerWins" : 1,
  "squeakerLosses" : 0,
  "subjectivePlayerType" : "Stronger"
}, {
  "name" : "Anne Lu",
  "points" : 1889,
  "maxPoints" : 223,
  "minPoints" : 96,
  "averagePoints" : 188.9,
  "standardDeviationOfPoints" : 46.04,
  "wins" : 8,
  "draws" : 0,
  "losses" : 2,
  "fails" : 0,
  "squeakerWins" : 1,
  "squeakerLosses" : 1,
  "subjectivePlayerType" : "Stronger"
}, {
  "name" : "Wouter van der Meer",
  "points" : 1872,
  "maxPoints" : 216,
  "minPoints" : 98,
  "averagePoints" : 187.2,
  "standardDeviationOfPoints" : 38.26,
  "wins" : 7,
  "draws" : 2,
  "losses" : 1,
  "fails" : 0,
  "squeakerWins" : 0,
  "squeakerLosses" : 1,
  "subjectivePlayerType" : "Stronger"
}, {
  "name" : "Noah Goldsmid",
  "points" : 2099,
  "maxPoints" : 226,
  "minPoints" : 150,
  "averagePoints" : 209.9,
  "standardDeviationOfPoints" : 21.08,
  "wins" : 9,
  "draws" : 1,
  "losses" : 0,
  "fails" : 0,
  "squeakerWins" : 0,
  "squeakerLosses" : 0,
  "subjectivePlayerType" : "Stronger"
}, {
  "name" : "Florian Molanus",
  "points" : 1751,
  "maxPoints" : 219,
  "minPoints" : 86,
  "averagePoints" : 175.1,
  "standardDeviationOfPoints" : 56.29,
  "wins" : 7,
  "draws" : 0,
  "losses" : 3,
  "fails" : 0,
  "squeakerWins" : 0,
  "squeakerLosses" : 0,
  "subjectivePlayerType" : "Stronger"
}, {
  "name" : "Tomek Czajka",
  "points" : 1859,
  "maxPoints" : 224,
  "minPoints" : 91,
  "averagePoints" : 185.9,
  "standardDeviationOfPoints" : 47.31,
  "wins" : 8,
  "draws" : 0,
  "losses" : 2,
  "fails" : 0,
  "squeakerWins" : 0,
  "squeakerLosses" : 0,
  "subjectivePlayerType" : "Stronger"
}, {
  "name" : "Ad van der Hoeven",
  "points" : 1940,
  "maxPoints" : 222,
  "minPoints" : 97,
  "averagePoints" : 194.0,
  "standardDeviationOfPoints" : 37.51,
  "wins" : 8,
  "draws" : 1,
  "losses" : 1,
  "fails" : 0,
  "squeakerWins" : 0,
  "squeakerLosses" : 0,
  "subjectivePlayerType" : "Stronger"
}, {
  "name" : "Boris de Wilde",
  "points" : 1905,
  "maxPoints" : 222,
  "minPoints" : 85,
  "averagePoints" : 190.5,
  "standardDeviationOfPoints" : 39.64,
  "wins" : 8,
  "draws" : 1,
  "losses" : 1,
  "fails" : 0,
  "squeakerWins" : 0,
  "squeakerLosses" : 0,
  "subjectivePlayerType" : "Stronger"
}, {
  "name" : "Frank Meert",
  "points" : 1741,
  "maxPoints" : 227,
  "minPoints" : 73,
  "averagePoints" : 174.1,
  "standardDeviationOfPoints" : 58.01,
  "wins" : 7,
  "draws" : 0,
  "losses" : 3,
  "fails" : 0,
  "squeakerWins" : 1,
  "squeakerLosses" : 1,
  "subjectivePlayerType" : "Stronger"
}, {
  "name" : "Tijs Lenssen",
  "points" : 1828,
  "maxPoints" : 226,
  "minPoints" : 94,
  "averagePoints" : 182.8,
  "standardDeviationOfPoints" : 47.84,
  "wins" : 7,
  "draws" : 1,
  "losses" : 2,
  "fails" : 0,
  "squeakerWins" : 1,
  "squeakerLosses" : 0,
  "subjectivePlayerType" : "Stronger"
}, {
  "name" : "Jorn Hoofwijk",
  "points" : 1756,
  "maxPoints" : 220,
  "minPoints" : 90,
  "averagePoints" : 175.6,
  "standardDeviationOfPoints" : 41.55,
  "wins" : 5,
  "draws" : 4,
  "losses" : 1,
  "fails" : 0,
  "squeakerWins" : 1,
  "squeakerLosses" : 0,
  "subjectivePlayerType" : "Stronger"
}, {
  "name" : "Fakih Karademir",
  "points" : 2046,
  "maxPoints" : 228,
  "minPoints" : 97,
  "averagePoints" : 204.6,
  "standardDeviationOfPoints" : 36.89,
  "wins" : 9,
  "draws" : 0,
  "losses" : 1,
  "fails" : 0,
  "squeakerWins" : 1,
  "squeakerLosses" : 0,
  "subjectivePlayerType" : "Stronger"
}, {
  "name" : "Pepijn Overbeeke",
  "points" : 1784,
  "maxPoints" : 214,
  "minPoints" : 94,
  "averagePoints" : 178.4,
  "standardDeviationOfPoints" : 44.89,
  "wins" : 7,
  "draws" : 1,
  "losses" : 2,
  "fails" : 0,
  "squeakerWins" : 4,
  "squeakerLosses" : 0,
  "subjectivePlayerType" : "Stronger"
}, {
  "name" : "Thijs Marinussen",
  "points" : 2178,
  "maxPoints" : 228,
  "minPoints" : 204,
  "averagePoints" : 217.8,
  "standardDeviationOfPoints" : 7.52,
  "wins" : 10,
  "draws" : 0,
  "losses" : 0,
  "fails" : 0,
  "squeakerWins" : 0,
  "squeakerLosses" : 0,
  "subjectivePlayerType" : "Stronger"
}, {
  "name" : "Corniel Nobel",
  "points" : 2134,
  "maxPoints" : 225,
  "minPoints" : 205,
  "averagePoints" : 213.4,
  "standardDeviationOfPoints" : 6.17,
  "wins" : 10,
  "draws" : 0,
  "losses" : 0,
  "fails" : 0,
  "squeakerWins" : 0,
  "squeakerLosses" : 0,
  "subjectivePlayerType" : "Stronger"
}, {
  "name" : "Henk Koops",
  "points" : 1810,
  "maxPoints" : 233,
  "minPoints" : 85,
  "averagePoints" : 181.0,
  "standardDeviationOfPoints" : 58.96,
  "wins" : 7,
  "draws" : 0,
  "losses" : 3,
  "fails" : 0,
  "squeakerWins" : 0,
  "squeakerLosses" : 1,
  "subjectivePlayerType" : "Stronger"
}, {
  "name" : "Tim Brouwer",
  "points" : 2148,
  "maxPoints" : 229,
  "minPoints" : 204,
  "averagePoints" : 214.8,
  "standardDeviationOfPoints" : 7.37,
  "wins" : 10,
  "draws" : 0,
  "losses" : 0,
  "fails" : 0,
  "squeakerWins" : 0,
  "squeakerLosses" : 0,
  "subjectivePlayerType" : "Stronger"
}, {
  "name" : "Jelmer Firet",
  "points" : 1871,
  "maxPoints" : 246,
  "minPoints" : 93,
  "averagePoints" : 187.1,
  "standardDeviationOfPoints" : 51.37,
  "wins" : 7,
  "draws" : 1,
  "losses" : 2,
  "fails" : 0,
  "squeakerWins" : 0,
  "squeakerLosses" : 1,
  "subjectivePlayerType" : "Stronger"
}, {
  "name" : "Rens van der Avoird",
  "points" : 1787,
  "maxPoints" : 223,
  "minPoints" : 87,
  "averagePoints" : 178.7,
  "standardDeviationOfPoints" : 56.45,
  "wins" : 7,
  "draws" : 0,
  "losses" : 3,
  "fails" : 0,
  "squeakerWins" : 0,
  "squeakerLosses" : 1,
  "subjectivePlayerType" : "Stronger"
}, {
  "name" : "Alvaro Begue",
  "points" : 1818,
  "maxPoints" : 215,
  "minPoints" : 94,
  "averagePoints" : 181.8,
  "standardDeviationOfPoints" : 47.37,
  "wins" : 7,
  "draws" : 1,
  "losses" : 2,
  "fails" : 0,
  "squeakerWins" : 0,
  "squeakerLosses" : 0,
  "subjectivePlayerType" : "Stronger"
} ]